argilla_server-2.8.0.dist-info/METADATA
argilla_server-2.8.0.dist-info/WHEEL
argilla_server-2.8.0.dist-info/entry_points.txt
argilla_server-2.8.0.dist-info/licenses/LICENSE
argilla_server-2.8.0.dist-info/licenses/LICENSE_HEADER
argilla_server/__init__.py
argilla_server/__main__.py
argilla_server/_app.py
argilla_server/_version.py
argilla_server/alembic.ini
argilla_server/alembic/env.py
argilla_server/alembic/script.py.mako
argilla_server/alembic/versions/1769ee58fbb4_create_workspaces_users_table.py
argilla_server/alembic/versions/1e629a913727_fix_suggestions_type_enum_values.py
argilla_server/alembic/versions/237f7c674d74_add_status_column_to_records_table.py
argilla_server/alembic/versions/3a8e2f9b5dea_create_questions_table.py
argilla_server/alembic/versions/3fc3c0839959_create_suggestions_table.py
argilla_server/alembic/versions/3ff6484f8b37_add_metadata_column_to_records_table.py
argilla_server/alembic/versions/45a12f74448b_add_distribution_column_to_datasets_table.py
argilla_server/alembic/versions/580a6553186f_add_datasets_users_table.py
argilla_server/alembic/versions/660d6c6b3360_add_metadata_column_to_datasets_table.py
argilla_server/alembic/versions/6ed1b8bf8e08_create_webhooks_table.py
argilla_server/alembic/versions/74694870197c_create_users_table.py
argilla_server/alembic/versions/7850ab5b42d9_create_vectors_settings_table.py
argilla_server/alembic/versions/7cbcccf8b57a_create_metadata_properties_table.py
argilla_server/alembic/versions/82a5a88a3fa5_create_workspaces_table.py
argilla_server/alembic/versions/84f6b9ff6076_add_last_activity_at_to_datasets_table.py
argilla_server/alembic/versions/8be56284dac0_create_records_table.py
argilla_server/alembic/versions/8c574ada5e5f_update_enum_columns.py
argilla_server/alembic/versions/ae5522b4c674_create_fields_table.py
argilla_server/alembic/versions/b8458008b60e_add_allow_extra_metadata_column_to_datasets_table.py
argilla_server/alembic/versions/b9099dc08489_create_datasets_table.py
argilla_server/alembic/versions/bda6fe24314e_create_vectors_table.py
argilla_server/alembic/versions/ca7293c38970_change_suggestions_score_column_to_json.py
argilla_server/alembic/versions/d00f819ccc67_update_responses_user_id_foreign_key.py
argilla_server/static/images/help-info/explain.png
argilla_server/static/images/help-info/similarity.png
argilla_server-2.8.0.dist-info/RECORD
