Metadata-Version: 2.1
Name: argilla-server
Version: 2.8.0
Summary: Open-source tool for exploring, labeling, and monitoring data for NLP projects.
Keywords: data-science,natural-language-processing,text-labeling,data-annotation,artificial-intelligence,knowledged-graph,developers-tools,human-in-the-loop,mlops
Author-Email: argilla <contact@argilla.io>
Maintainer-Email: argilla <contact@argilla.io>
License: Apache-2.0
Project-URL: homepage, https://www.argilla.io
Project-URL: documentation, https://docs.argilla.io
Project-URL: repository, https://github.com/argilla-io/argilla
Requires-Python: >=3.9
Requires-Dist: fastapi~=0.115.0
Requires-Dist: pydantic~=2.9.0
Requires-Dist: pydantic-settings~=2.6.0
Requires-Dist: uvicorn[standard]~=0.32.0
Requires-Dist: opensearch-py~=2.0.0
Requires-Dist: elasticsearch8[async]~=8.7.0
Requires-Dist: brotli-asgi~=1.4.0
Requires-Dist: backoff~=2.2.0
Requires-Dist: alembic~=1.13.0
Requires-Dist: SQLAlchemy~=2.0.0
Requires-Dist: greenlet~=3.1.0
Requires-Dist: aiosqlite==0.20.0
Requires-Dist: aiofiles~=24.1.0
Requires-Dist: PyYAML<6.1.0,>=5.4.1
Requires-Dist: python-jose[cryptography]~=3.3.0
Requires-Dist: bcrypt~=4.2.0
Requires-Dist: python-multipart~=0.0.16
Requires-Dist: httpx~=0.27.0
Requires-Dist: oauthlib~=3.2.0
Requires-Dist: social-auth-core~=4.5.0
Requires-Dist: rq~=1.16.2
Requires-Dist: psutil<5.10,~=5.8
Requires-Dist: rich!=13.1.0
Requires-Dist: typer<0.10.0,>=0.6.0
Requires-Dist: packaging>=23.2
Requires-Dist: standardwebhooks>=1.0.0
Requires-Dist: datasets>=3.0.1
Requires-Dist: pillow>=10.4.0
Requires-Dist: huggingface-hub>=0.26.2
Requires-Dist: Jinja2>=3.1.4
Provides-Extra: postgresql
Requires-Dist: psycopg2~=2.9.0; extra == "postgresql"
Requires-Dist: asyncpg~=0.30.0; extra == "postgresql"
